{"seed": 4, "iou": [[1.0, 0.1284409648441358, 0.03305266516404287, 0.039348659437930575], [0.1284409648441358, 1.0, 0.42717431835124364, 0.46502057574155914], [0.03305266516404287, 0.42717431835124364, 1.0, 0.9136633412152622], [0.039348659437930575, 0.46502057574155914, 0.9136633412152622, 1.0]], "views": [{"agent": 0, "facts": [], "raw": " The image depicts a scene from a video game. The background is a dark gray color, which serves as a neutral backdrop for the various elements within the scene. There are several objects and characters present in the image.\n\nStarting from the left side of the image, there is a small, rectangular object that appears to be a small, metallic or plastic object. This object is white in color and has a small, circular hole in the center.\n\nMoving to the center of the image, there is a larger, rectangular object that resembles a small, rectangular box or a small, rectangular container. This object is also white in color and has a small, circular hole in the center.\n\nTo the right of the central object, there is a person. The person is wearing a dark", "true_facts": [{"cls": "truck", "color": "green"}], "box": [7.469875513572482, 9.056851628699263, 711.4698755135724, 471.0568516286993]}, {"agent": 1, "facts": [{"object": "bus", "attr": "green", "confidence": 0.8}, {"object": "bus", "attr": "green", "confidence": 0.8}, {"object": "bus", "attr": "yellow", "confidence": 0.8}, {"object": "bus", "attr": "yellow", "confidence": 0.8}], "raw": " The image depicts a road scene with three vehicles and one person. The vehicles are as follows:\n\n1. **Green Bus**: The first vehicle is a green bus. It is traveling on the road, moving from left to right. The bus has a rectangular shape with a green color.\n\n2. **Yellow Bus**: The second vehicle is a yellow bus. It is also traveling on the road, moving from left to right. The bus has a rectangular shape with a yellow color.\n\n3. **Person**: The third vehicle is a person. The person is standing on the road, facing the camera. The person is wearing a blue shirt and has short hair.\n\nThe road is marked with white dashed lines, indicating lanes and boundaries. The background is a dark gray color, which", "true_facts": [{"cls": "truck", "color": "green"}, {"cls": "truck", "color": "yellow"}], "box": [342.03179751903815, 270.6430205958135, 1046.0317975190383, 732.6430205958135]}, {"agent": 2, "facts": [{"object": "car", "attr": "green", "confidence": 0.8}, {"object": "car", "attr": "yellow", "confidence": 0.8}, {"object": "car", "attr": "green", "confidence": 0.8}, {"object": "car", "attr": "yellow", "confidence": 0.8}], "raw": " The image depicts a scene with three distinct vehicles and one person. The vehicles are as follows:\n\n1. **Green Car**: Positioned on the left side of the image, this car is a standard-sized vehicle with a rectangular shape. It has a sleek design with a prominent front grille and a small headlight. The car is stationary, and its color is green.\n\n2. **Yellow Car**: Located on the right side of the image, this car is a smaller, more compact vehicle with a rounded shape. It has a similar design to the green car but is slightly smaller. The yellow car is also stationary.\n\n3. **Person**: The third vehicle is a person, positioned in the center of the image. The person is wearing a white shirt and appears to be", "true_facts": [{"cls": "truck", "color": "green"}, {"cls": "truck", "color": "yellow"}], "box": [521.1211351568169, 361.71695857472133, 1225.1211351568168, 823.7169585747213]}, {"agent": 3, "facts": [{"object": "car", "attr": "green", "confidence": 0.8}, {"object": "car", "attr": "green", "confidence": 0.8}, {"object": "car", "attr": "yellow", "confidence": 0.8}, {"object": "car", "attr": "yellow", "confidence": 0.8}, {"object": "car", "attr": "green", "confidence": 0.8}, {"object": "car", "attr": "blue", "confidence": 0.8}, {"object": "car", "attr": "blue", "confidence": 0.8}], "raw": " The image depicts a scene from a video game. The primary objects in the image are vehicles and people.\n\n### Vehicles:\n1. **Green Car**: Positioned on the left side of the image, the green car is a typical vehicle with a rectangular shape and a flat roof. It has four wheels, a windshield, and a driver's seat.\n2. **Yellow Car**: Located on the right side of the image, the yellow car is a similar vehicle to the green car. It has a similar design with four wheels, a windshield, and a driver's seat.\n3. **Blue Car**: Positioned in the middle of the image, the blue car is a different type of vehicle. It has a rounded shape and a flat roof. It has four", "true_facts": [{"cls": "truck", "color": "green"}, {"cls": "truck", "color": "yellow"}], "box": [499.30479713688294, 354.98166006526895, 1203.3047971368828, 816.9816600652689]}], "stats_snapshot": {"calls": 21, "parse_fail": 1, "retries": 1, "tok_in": 18704, "tok_out": 3360, "wall_s": 240.45039796829224}}